{"coord":{"lon":9.74,"lat":52.37},"weather":[{"id":310,"main":"Drizzle","description":"light intensity drizzle rain","icon":"09n"},{"id":701,"main":"Mist","description":"mist","icon":"50n"}],"base":"stations","main":{"temp":279.98,"pressure":988,"humidity":93,"temp_min":278.15,"temp_max":282.15},"visibility":10000,"wind":{"speed":2.6,"deg":190},"clouds":{"all":75},"dt":1515095400,"sys":{"type":1,"id":4893,"message":0.0103,"country":"DE","sunrise":1515051010,"sunset":1515079367},"id":3221033,"name":"Hanover","cod":200}